odoo/addons/contract_section/README.rst
odoo/addons/contract_section/__init__.py
odoo/addons/contract_section/__manifest__.py
odoo/addons/contract_section/i18n/contract_section.pot
odoo/addons/contract_section/i18n/de.po
odoo/addons/contract_section/i18n/it.po
odoo/addons/contract_section/models/__init__.py
odoo/addons/contract_section/models/account_analytic_account.py
odoo/addons/contract_section/models/account_analytic_contract_line.py
odoo/addons/contract_section/readme/CONTRIBUTORS.rst
odoo/addons/contract_section/readme/DESCRIPTION.rst
odoo/addons/contract_section/readme/USAGE.rst
odoo/addons/contract_section/static/description/icon.png
odoo/addons/contract_section/static/description/index.html
odoo/addons/contract_section/tests/__init__.py
odoo/addons/contract_section/tests/test_contract.py
odoo/addons/contract_section/views/account_analytic_account.xml
odoo/addons/contract_section/views/account_analytic_contract.xml
odoo11_addon_contract_section-11.0.1.0.1.dist-info/METADATA
odoo11_addon_contract_section-11.0.1.0.1.dist-info/WHEEL
odoo11_addon_contract_section-11.0.1.0.1.dist-info/top_level.txt
odoo11_addon_contract_section-11.0.1.0.1.dist-info/RECORD
